dash/__init__.py
dash/_callback_context.py
dash/_configs.py
dash/_utils.py
dash/_watch.py
dash/dash.py
dash/dependencies.py
dash/exceptions.py
dash/extract-meta.js
dash/favicon.ico
dash/fingerprint.py
dash/resources.py
dash/version.py
dash/development/__init__.py
dash/development/_all_keywords.py
dash/development/_py_components_generation.py
dash/development/_r_components_generation.py
dash/development/base_component.py
dash/development/build_process.py
dash/development/component_generator.py
dash/development/component_loader.py
dash/testing/__init__.py
dash/testing/application_runners.py
dash/testing/browser.py
dash/testing/composite.py
dash/testing/consts.py
dash/testing/dash_page.py
dash/testing/errors.py
dash/testing/newhooks.py
dash/testing/plugin.py
dash/testing/wait.py
dash_tokamak-1.6.0.dist-info/LICENSE
dash_tokamak-1.6.0.dist-info/METADATA
dash_tokamak-1.6.0.dist-info/WHEEL
dash_tokamak-1.6.0.dist-info/entry_points.txt
dash_tokamak-1.6.0.dist-info/top_level.txt
dash_tokamak-1.6.0.dist-info/RECORD
