Metadata-Version: 2.1
Name: dash-tokamak
Version: 1.6.0
Summary: Dash without the annoying bits. Main goals of this fork are (1) to enable
Home-page: https://github.com/ProbonoBonobo/dash
Author: Chris Parmer, Kevin Zeidler
Author-email: 
License: MIT
Platform: UNKNOWN
Classifier: Development Status :: 5 - Production/Stable
Classifier: Environment :: Web Environment
Classifier: Framework :: Dash
Classifier: Framework :: Flask
Classifier: Intended Audience :: Developers
Classifier: Intended Audience :: Education
Classifier: Intended Audience :: Financial and Insurance Industry
Classifier: Intended Audience :: Healthcare Industry
Classifier: Intended Audience :: Manufacturing
Classifier: Intended Audience :: Science/Research
Classifier: License :: OSI Approved :: MIT License
Classifier: Programming Language :: Python
Classifier: Programming Language :: Python :: 2
Classifier: Programming Language :: Python :: 2.7
Classifier: Programming Language :: Python :: 3
Classifier: Programming Language :: Python :: 3.3
Classifier: Programming Language :: Python :: 3.4
Classifier: Programming Language :: Python :: 3.5
Classifier: Programming Language :: Python :: 3.6
Classifier: Programming Language :: Python :: 3.7
Classifier: Topic :: Database :: Front-Ends
Classifier: Topic :: Office/Business :: Financial :: Spreadsheet
Classifier: Topic :: Scientific/Engineering :: Visualization
Classifier: Topic :: Software Development :: Libraries :: Application Frameworks
Classifier: Topic :: Software Development :: Widget Sets
Requires-Dist: Flask (>=1.0.2)
Requires-Dist: flask-compress
Requires-Dist: plotly
Requires-Dist: dash-renderer (==1.2.0)
Requires-Dist: dash-core-components (==1.5.0)
Requires-Dist: dash-html-components (==1.0.1)
Requires-Dist: dash-table (==4.5.0)
Requires-Dist: future
Provides-Extra: dev
Requires-Dist: dash-flow-example (==0.0.5) ; extra == 'dev'
Requires-Dist: dash-dangerously-set-inner-html ; extra == 'dev'
Requires-Dist: mock ; extra == 'dev'
Requires-Dist: flake8 ; extra == 'dev'
Requires-Dist: PyYAML (>=5.1.1) ; extra == 'dev'
Requires-Dist: fire ; extra == 'dev'
Requires-Dist: coloredlogs ; extra == 'dev'
Requires-Dist: pylint (==1.9.4) ; (python_version < "3.7") and extra == 'dev'
Requires-Dist: virtualenv ; (python_version == "2.7") and extra == 'dev'
Requires-Dist: pylint (==2.3.1) ; (python_version == "3.7") and extra == 'dev'
Requires-Dist: astroid (==2.2.5) ; (python_version == "3.7") and extra == 'dev'
Provides-Extra: testing
Requires-Dist: pytest ; extra == 'testing'
Requires-Dist: pytest-sugar ; extra == 'testing'
Requires-Dist: pytest-mock ; extra == 'testing'
Requires-Dist: lxml ; extra == 'testing'
Requires-Dist: selenium (>=3.141.0) ; extra == 'testing'
Requires-Dist: percy ; extra == 'testing'
Requires-Dist: requests[security] ; extra == 'testing'
Requires-Dist: beautifulsoup4 ; extra == 'testing'
Requires-Dist: waitress ; extra == 'testing'
